odoo/addons/product_contract/README.rst
odoo/addons/product_contract/__init__.py
odoo/addons/product_contract/__manifest__.py
odoo/addons/product_contract/i18n/de.po
odoo/addons/product_contract/i18n/es.po
odoo/addons/product_contract/i18n/fi.po
odoo/addons/product_contract/i18n/fr.po
odoo/addons/product_contract/i18n/hi_IN.po
odoo/addons/product_contract/i18n/hr.po
odoo/addons/product_contract/i18n/hr_HR.po
odoo/addons/product_contract/i18n/it.po
odoo/addons/product_contract/i18n/nl.po
odoo/addons/product_contract/i18n/nl_NL.po
odoo/addons/product_contract/i18n/product_contract.pot
odoo/addons/product_contract/i18n/pt.po
odoo/addons/product_contract/i18n/pt_BR.po
odoo/addons/product_contract/i18n/ru.po
odoo/addons/product_contract/i18n/tr.po
odoo/addons/product_contract/i18n/tr_TR.po
odoo/addons/product_contract/migrations/12.0.2.0.0/pre-migration.py
odoo/addons/product_contract/migrations/12.0.3.0.0/pre-migration.py
odoo/addons/product_contract/migrations/12.0.4.0.0/pre-migration.py
odoo/addons/product_contract/models/__init__.py
odoo/addons/product_contract/models/contract.py
odoo/addons/product_contract/models/contract_line.py
odoo/addons/product_contract/models/product_template.py
odoo/addons/product_contract/models/res_company.py
odoo/addons/product_contract/models/res_config_settings.py
odoo/addons/product_contract/models/sale_order.py
odoo/addons/product_contract/models/sale_order_line.py
odoo/addons/product_contract/readme/CONTRIBUTORS.rst
odoo/addons/product_contract/readme/DESCRIPTION.rst
odoo/addons/product_contract/readme/USAGE.rst
odoo/addons/product_contract/static/description/icon.png
odoo/addons/product_contract/static/description/index.html
odoo/addons/product_contract/tests/__init__.py
odoo/addons/product_contract/tests/test_product.py
odoo/addons/product_contract/tests/test_sale_order.py
odoo/addons/product_contract/views/contract.xml
odoo/addons/product_contract/views/product_template.xml
odoo12_addon_product_contract-12.0.5.3.1.dist-info/METADATA
odoo12_addon_product_contract-12.0.5.3.1.dist-info/WHEEL
odoo12_addon_product_contract-12.0.5.3.1.dist-info/top_level.txt
odoo12_addon_product_contract-12.0.5.3.1.dist-info/RECORD
